actlog/__init__.py
actlog/activity_logger.py
actlog/cli.py
actlog/constants.py
actlog/daemon.py
actlog/database.py
actlog/dbmodel.py
actlog/external_dependencies.py
actlog/file_importer.py
actlog/helpformatter.py
actlog/image_timestring.py
actlog/log.py
actlog/monitor.py
actlog/passwordcli.py
actlog/screenshots.py
actlog/timestr.py
actlog/view.py
actlog/webpassword.py
actlog/webserver.py
actlog/activedetector/__init__.py
actlog/activedetector/custom.py
actlog/activedetector/dbusscreensaver.py
actlog/activedetector/executablerunning.py
actlog/activedetector/xprintidle.py
actlog/migrations/README
actlog/migrations/alembic.ini
actlog/migrations/env.py
actlog/migrations/script.py.mako
actlog/migrations/versions/bc010f7fee42_added_configuration.py
actlog/migrations/versions/ca8af9b96aef_initial_migration.py
actlog/frontend/build/.gitignore
actlog/frontend/build/favicon.png
actlog/frontend/build/index.html
actlog/frontend/build/login.html
actlog/frontend/build/_app/version.json
actlog/frontend/build/_app/immutable/assets/2.6a109d73.css
actlog/frontend/build/_app/immutable/assets/3.22893d2b.css
actlog/frontend/build/_app/immutable/assets/_page.22893d2b.css
actlog/frontend/build/_app/immutable/assets/_page.f3378c30.css
actlog/frontend/build/_app/immutable/assets/bootstrap.5ffef9fa.css
actlog/frontend/build/_app/immutable/assets/datepicker-bs5.fea003ec.css
actlog/frontend/build/_app/immutable/chunks/bootstrap.0bb19e3e.js.map
actlog/frontend/build/_app/immutable/chunks/bootstrap.esm.1b4953f5.js
actlog/frontend/build/_app/immutable/chunks/bootstrap.esm.1b4953f5.js.map
actlog/frontend/build/_app/immutable/chunks/datepicker-bs5.8012b429.js.map
actlog/frontend/build/_app/immutable/chunks/index.19816e33.js
actlog/frontend/build/_app/immutable/chunks/index.19816e33.js.map
actlog/frontend/build/_app/immutable/chunks/index.7582688d.js
actlog/frontend/build/_app/immutable/chunks/index.7582688d.js.map
actlog/frontend/build/_app/immutable/chunks/preload-helper.a4192956.js
actlog-0.0.4.dist-info/METADATA
actlog-0.0.4.dist-info/WHEEL
actlog-0.0.4.dist-info/entry_points.txt
actlog-0.0.4.dist-info/licenses/LICENSE
actlog-0.0.4.dist-info/RECORD
