Metadata-Version: 2.1
Name: actlog
Version: 0.0.4
Summary: An activity log that shows you what you did when
Project-URL: Homepage, https://github.com/pmorch/actlog
Project-URL: Bug Tracker, https://github.com/pmorch/actlog/issues
Author-email: Peter Valdemar Mørch <peter@morch.com>
License-File: LICENSE
Classifier: Development Status :: 4 - Beta
Classifier: Environment :: X11 Applications
Classifier: Intended Audience :: End Users/Desktop
Classifier: License :: OSI Approved :: MIT License
Classifier: Operating System :: POSIX
Classifier: Programming Language :: JavaScript
Classifier: Programming Language :: Python :: 3
Classifier: Topic :: Desktop Environment
Classifier: Topic :: System :: Monitoring
Requires-Python: >=3.8
Requires-Dist: alembic
Requires-Dist: argon2-cffi
Requires-Dist: dateparser
Requires-Dist: flask
Requires-Dist: flask-cors
Requires-Dist: furl
Requires-Dist: gunicorn
Requires-Dist: python-pidfile
Requires-Dist: pyyaml
Requires-Dist: sqlalchemy
Provides-Extra: dev
Requires-Dist: build; extra == 'dev'
Requires-Dist: pip-tools; extra == 'dev'
Requires-Dist: pyright; extra == 'dev'
